nonebot_plugin_pluginupdatecheck/__init__.py
nonebot_plugin_pluginupdatecheck/config.py
nonebot_plugin_pluginupdatecheck/tool.py
nonebot_plugin_pluginupdatecheck-0.1.2.dist-info/WHEEL
nonebot_plugin_pluginupdatecheck-0.1.2.dist-info/METADATA
nonebot_plugin_pluginupdatecheck-0.1.2.dist-info/RECORD
