Metadata-Version: 2.1
Name: nonebot-plugin-pluginupdatecheck
Version: 0.1.2
Summary: A plugin of chatbot based on nonebot2 framework,it can check the updateable plugins already installed.Also can install new plugins.
Author: xi-yue-233
Author-email: 1004514855@qq.com
Requires-Python: >=3.9,<4.0
Classifier: Programming Language :: Python :: 3
Classifier: Programming Language :: Python :: 3.9
Classifier: Programming Language :: Python :: 3.10
Classifier: Programming Language :: Python :: 3.11
Requires-Dist: nonebot-adapter-onebot (>=2.2.0,<3.0.0)
Requires-Dist: nonebot2 (>=2.0.0rc2,<3.0.0)
Requires-Dist: numpy (>=1.24.3,<2.0.0)
Requires-Dist: toml (>=0.10.2,<0.11.0)
